scriptTimer/ScriptTimer.py
scriptTimer/__init__.py
scriptTimer-0.0.1.dist-info/LICENSE
scriptTimer-0.0.1.dist-info/METADATA
scriptTimer-0.0.1.dist-info/WHEEL
scriptTimer-0.0.1.dist-info/top_level.txt
scriptTimer-0.0.1.dist-info/RECORD
