Metadata-Version: 2.1
Name: scriptTimer
Version: 0.0.1
Summary: A script that records time taken by python scripts
Home-page: https://github.com/kartik-99/scriptTimer
Author: Kartik
Author-email: kartik42sharma@gmail.com
License: UNKNOWN
Platform: UNKNOWN
Classifier: Programming Language :: Python :: 3
Classifier: License :: OSI Approved :: MIT License
Classifier: Operating System :: OS Independent
Requires-Python: >=3.6
License-File: LICENSE
